solar/__init__.py
solar/cli.py
solar/ai/__init__.py
solar/ai/base.py
solar/ai/factory.py
solar/ai/gemini.py
solar/ai/openai.py
solar/commands/__init__.py
solar/commands/config.py
solar/commands/create.py
solar/commands/delete.py
solar/commands/edit.py
solar/commands/init.py
solar/commands/list.py
solar/commands/new.py
solar/commands/run.py
solar/commands/style.py
solar/commands/supabase.py
solar/generator/__init__.py
solar/generator/page.py
solar/generator/project.py
solar/utils/__init__.py
solar/utils/config.py
solar/utils/flutter.py
solar/utils/project.py
solar/utils/supabase_client.py
solar_cli_eldermarx-1.1.1.dist-info/METADATA
solar_cli_eldermarx-1.1.1.dist-info/WHEEL
solar_cli_eldermarx-1.1.1.dist-info/entry_points.txt
solar_cli_eldermarx-1.1.1.dist-info/top_level.txt
solar_cli_eldermarx-1.1.1.dist-info/RECORD
