Metadata-Version: 2.4
Name: solar-cli-eldermarx
Version: 1.1.1
Summary: SOLAR by Elder Marx - Create Flutter apps with natural language
Author-email: Elder Marx <eldermarx1@gmail.com>
License: MIT
Keywords: flutter,cli,code-generator,ai,natural-language
Classifier: Development Status :: 4 - Beta
Classifier: Environment :: Console
Classifier: Intended Audience :: Developers
Classifier: License :: OSI Approved :: MIT License
Classifier: Operating System :: OS Independent
Classifier: Programming Language :: Python :: 3
Classifier: Programming Language :: Python :: 3.9
Classifier: Programming Language :: Python :: 3.10
Classifier: Programming Language :: Python :: 3.11
Classifier: Programming Language :: Python :: 3.12
Classifier: Topic :: Software Development :: Code Generators
Requires-Python: >=3.9
Requires-Dist: click>=8.1.0
Requires-Dist: rich>=13.0.0
Requires-Dist: google-generativeai>=0.8.0
Requires-Dist: openai>=1.0.0
Requires-Dist: python-dotenv>=1.0.0
Requires-Dist: pyyaml>=6.0
Requires-Dist: supabase>=2.0.0
Requires-Dist: requests>=2.31.0
Provides-Extra: dev
Requires-Dist: pytest>=7.0.0; extra == "dev"
Requires-Dist: black>=23.0.0; extra == "dev"
Requires-Dist: isort>=5.12.0; extra == "dev"
